arcadedb_embedded/__init__.py
arcadedb_embedded-0.0.2.dist-info/METADATA
arcadedb_embedded-0.0.2.dist-info/WHEEL
arcadedb_embedded-0.0.2.dist-info/top_level.txt
arcadedb_embedded-0.0.2.dist-info/RECORD
