Metadata-Version: 2.4
Name: arcadedb-embedded
Version: 0.0.2
Summary: ArcadeDB embedded multi-model database with bundled JRE - no Java installation required (PLACEHOLDER VERSION)
Author-email: Arcade Data Ltd <info@arcadedata.com>
License: Apache-2.0
Project-URL: Homepage, https://github.com/humemai/arcadedb-embedded-python
Project-URL: Documentation, https://humemai.github.io/arcadedb-embedded-python/
Project-URL: Repository, https://github.com/humemai/arcadedb-embedded-python
Project-URL: Bug Tracker, https://github.com/humemai/arcadedb-embedded-python/issues
Project-URL: ArcadeDB Upstream, https://github.com/ArcadeData/arcadedb
Keywords: database,graph,document,multi-model,nosql,arcadedb,embedded,jre,java
Classifier: Development Status :: 1 - Planning
Classifier: Intended Audience :: Developers
Classifier: License :: OSI Approved :: Apache Software License
Classifier: Programming Language :: Python :: 3
Classifier: Programming Language :: Python :: 3.8
Classifier: Programming Language :: Python :: 3.9
Classifier: Programming Language :: Python :: 3.10
Classifier: Programming Language :: Python :: 3.11
Classifier: Programming Language :: Python :: 3.12
Classifier: Topic :: Database
Classifier: Topic :: Software Development :: Libraries :: Python Modules
Requires-Python: >=3.8
